dvrd_imap/__init__.py
dvrd_imap/models/__init__.py
dvrd_imap/models/exception.py
dvrd_imap/models/imap_filter.py
dvrd_imap/models/imap_message.py
dvrd_imap/models/imap_server.py
dvrd_imap/models/types.py
dvrd_imap-1.1.5.dist-info/licenses/LICENSE
dvrd_imap-1.1.5.dist-info/METADATA
dvrd_imap-1.1.5.dist-info/WHEEL
dvrd_imap-1.1.5.dist-info/top_level.txt
dvrd_imap-1.1.5.dist-info/RECORD
