Metadata-Version: 2.4
Name: dvrd_imap
Version: 1.1.5
Summary: Object oriented wrapper for imaplib
Author-email: Dave van Rijn Development <develop@davevanrijn.nl>
Project-URL: Homepage, https://bitbucket.org/Naampie/dvrd-imap
Project-URL: Issues, https://bitbucket.org/Naampie/dvrd-imap/issues
Classifier: Programming Language :: Python :: 3.11
Classifier: License :: OSI Approved :: BSD License
Classifier: Operating System :: OS Independent
Requires-Python: >=3.11
License-File: LICENSE
Requires-Dist: chardet
Dynamic: license-file
